serverly/__init__.py
serverly/default_sites.py
serverly/err.py
serverly/objects.py
serverly/plugins.py
serverly/stater.py
serverly/statistics.py
serverly/utils.py
serverly/user/__init__.py
serverly/user/api.py
serverly/user/auth.py
serverly/user/mail.py
serverly/user/session.py
serverly-0.4.6.dist-info/LICENSE
serverly-0.4.6.dist-info/METADATA
serverly-0.4.6.dist-info/WHEEL
serverly-0.4.6.dist-info/top_level.txt
serverly-0.4.6.dist-info/RECORD
