Metadata-Version: 2.1
Name: serverly
Version: 0.4.6
Summary: A really simple-to-use HTTP-server
Home-page: https://github.com/mithem/PyServer
Author: mithem
Author-email: miguel.themann@gmail.com
License: UNKNOWN
Platform: UNKNOWN
Classifier: Programming Language :: Python :: 3
Classifier: License :: OSI Approved :: MIT License
Classifier: Operating System :: OS Independent
Requires-Python: >=3.6
